cppmdlp/CPPFImdlp.cpp
cppmdlp/CPPFImdlp.h
cppmdlp/Metrics.cpp
cppmdlp/Metrics.h
cppmdlp/typesFImdlp.h
fimdlp/Factorize.cpp
fimdlp/Factorize.h
fimdlp/__init__.py
fimdlp/_version.py
fimdlp/cfimdlp.pyx
fimdlp/cppfimdlp.cpython-310-darwin.so
fimdlp/mdlp.py
fimdlp/tests/FImdlp_test.py
fimdlp/tests/__init__.py
FImdlp-0.9.3.dist-info/LICENSE
FImdlp-0.9.3.dist-info/METADATA
FImdlp-0.9.3.dist-info/WHEEL
FImdlp-0.9.3.dist-info/top_level.txt
FImdlp-0.9.3.dist-info/RECORD
