Metadata-Version: 2.1
Name: FImdlp
Version: 0.9.3
Author-email: Ricardo Montañana <ricardo.montanana@alu.uclm.es>
Project-URL: Home, https://github.com/doctorado-ml/FImdlp
Classifier: Development Status :: 3 - Alpha
Classifier: Intended Audience :: Science/Research
Classifier: Intended Audience :: Developers
Classifier: Topic :: Software Development
Classifier: Topic :: Scientific/Engineering
Classifier: License :: OSI Approved :: MIT License
Classifier: Natural Language :: English
Classifier: Operating System :: OS Independent
Classifier: Programming Language :: Python
Classifier: Programming Language :: Python
Classifier: Programming Language :: Python :: 3.9
Classifier: Programming Language :: Python :: 3.10
Requires-Python: >=3.9
License-File: LICENSE
